setup.py
distributions/Binomialdistribution.py
distributions/Gaussiandistribution.py
distributions/Generaldistribution.py
distributions/__init__.py
gregetsuro_dist_test1.egg-info/PKG-INFO
gregetsuro_dist_test1.egg-info/SOURCES.txt
gregetsuro_dist_test1.egg-info/dependency_links.txt
gregetsuro_dist_test1.egg-info/not-zip-safe
gregetsuro_dist_test1.egg-info/top_level.txt